CHANGES.rst
LICENSE.rst
MANIFEST.in
README.rst
bootstrap.py
buildout.cfg
constraints_plone43.txt
constraints_plone51.txt
constraints_plone52.txt
requirements.txt
setup.py
src/lineage/__init__.py
src/lineage.registry.egg-info/PKG-INFO
src/lineage.registry.egg-info/SOURCES.txt
src/lineage.registry.egg-info/dependency_links.txt
src/lineage.registry.egg-info/entry_points.txt
src/lineage.registry.egg-info/namespace_packages.txt
src/lineage.registry.egg-info/not-zip-safe
src/lineage.registry.egg-info/requires.txt
src/lineage.registry.egg-info/top_level.txt
src/lineage/registry/__init__.py
src/lineage/registry/configure.zcml
src/lineage/registry/proxy.py
src/lineage/registry/proxy.rst
src/lineage/registry/setuphandlers.py
src/lineage/registry/subscribers.py
src/lineage/registry/testing.py
src/lineage/registry/tests.py
src/lineage/registry/upgrades.py
src/lineage/registry/utils.py
src/lineage/registry/profiles/default/metadata.xml
src/lineage/registry/profiles/uninstall/.gitkeep